Metadata-Version: 2.1
Name: odoo8-addon-sale-partner-incoterm
Version: 8.0.1.0.0.99.dev22
Summary: Set the customer preferred incoterm on each sales order
Home-page: https://github.com/oca/sale-workflow
Author: Opener B.V.,Odoo Community Association (OCA)
Author-email: support@odoo-community.org
License: AGPL-3
Platform: UNKNOWN
Classifier: Programming Language :: Python
Classifier: Framework :: Odoo
Classifier: Framework :: Odoo :: 8.0
Classifier: License :: OSI Approved :: GNU Affero General Public License v3
Requires-Python: ~=2.7
Requires-Dist: odoo (<9.0a,>=8.0a)
